aps_viewer_sdk/__init__.py
aps_viewer_sdk/client.py
aps_viewer_sdk/helper.py
aps_viewer_sdk/plugins/__init__.py
aps_viewer_sdk/plugins/base.py
aps_viewer_sdk/plugins/draw_2d_circles/__init__.py
aps_viewer_sdk/plugins/draw_2d_circles/circle_markers_2d.js
aps_viewer_sdk/plugins/draw_3d_spheres/__init__.py
aps_viewer_sdk/plugins/draw_3d_spheres/sphere_markers_3d.js
aps_viewer_sdk/plugins/overlay_meshes/__init__.py
aps_viewer_sdk/plugins/overlay_meshes/overlay_meshes.js
aps_viewer_sdk/templates/viewer.html
aps_viewer_sdk-0.1.1.dist-info/METADATA
aps_viewer_sdk-0.1.1.dist-info/WHEEL
aps_viewer_sdk-0.1.1.dist-info/licenses/LICENSE.txt
aps_viewer_sdk-0.1.1.dist-info/RECORD
