Metadata-Version: 2.4
Name: aps-viewer-sdk
Version: 0.1.1
Summary: Add your description here
License-File: LICENSE.txt
Requires-Python: >=3.12
Requires-Dist: aps-automation-sdk==0.1.1
Requires-Dist: requests>=2.32.5
